llama_index/py.typed
llama_index/vector_stores/mongodb/__init__.py
llama_index/vector_stores/mongodb/base.py
llama_index/vector_stores/mongodb/index.py
llama_index/vector_stores/mongodb/pipelines.py
llama_index_vector_stores_mongodb-0.9.0.dist-info/METADATA
llama_index_vector_stores_mongodb-0.9.0.dist-info/WHEEL
llama_index_vector_stores_mongodb-0.9.0.dist-info/licenses/LICENSE
llama_index_vector_stores_mongodb-0.9.0.dist-info/RECORD
