Metadata-Version: 2.4
Name: llama-index-vector-stores-mongodb
Version: 0.9.0
Summary: llama-index vector_stores mongodb integration
Author: The MongoDB Python Team
License-Expression: MIT
License-File: LICENSE
Requires-Python: <4.0,>=3.9
Requires-Dist: llama-index-core<0.15.0,>=0.13.0
Requires-Dist: pymongo<5,>=4.9.0
